setup.cfg
setup.py
plankton/__init__.py
plankton/app.py
plankton/plankton_server.py
plankton/routes.py
plankton/settings.py
plankton.egg-info/PKG-INFO
plankton.egg-info/SOURCES.txt
plankton.egg-info/dependency_links.txt
plankton.egg-info/not-zip-safe
plankton.egg-info/requires.txt
plankton.egg-info/top_level.txt
plankton/wkhtmltopdf/__init__.py
plankton/wkhtmltopdf/utils.py
plankton/wkhtmltopdf/validators.py
plankton/wkhtmltopdf/views.py
scripts/plankton-server