Metadata-Version: 1.1
Name: plankton
Version: 0.1.2
Summary: Plankton - wkhtmltopdf REST service
Home-page: https://github.com/django-stars/plankton
Author: Dmytro Upolovnikov
Author-email: dmitry.upolovnikov@djangostars.com
License: Apache License 2.0
Download-URL: https://github.com/django-stars/plankton/tarball/0.1.2
Keywords: html to pdf,wkhtmltopdf,pdf,rest
Platform: UNKNOWN
